prophet_freddy.libs/libtbbmalloc-a5fcf397.so.2
prophet_freddy.libs/libtbb-efb225b7.so.2
prophet/diagnostics.py
prophet/plot.py
prophet/forecaster.py
prophet/hdays.py
prophet/models.py
prophet/utilities.py
prophet/make_holidays.py
prophet/__init__.py
prophet/serialize.py
prophet/tests/test_prophet.py
prophet/tests/test_diagnostics.py
prophet/tests/data2.csv
prophet/tests/serialized_model_v0.7.1.json
prophet/tests/test_serialize.py
prophet/tests/test_utilities.py
prophet/tests/serialized_model_v0.6.1.dev0.json
prophet/tests/__init__.py
prophet/tests/data.csv
prophet/stan_model/prophet_model.bin
prophet/stan_model/cmdstan-2.26.1/stan/lib/stan_math/lib/tbb/dynamic_link.d
prophet/stan_model/cmdstan-2.26.1/stan/lib/stan_math/lib/tbb/private_server.d
prophet/stan_model/cmdstan-2.26.1/stan/lib/stan_math/lib/tbb/itt_notify_malloc.o
prophet/stan_model/cmdstan-2.26.1/stan/lib/stan_math/lib/tbb/tbbvars.csh
prophet/stan_model/cmdstan-2.26.1/stan/lib/stan_math/lib/tbb/libtbbmalloc_proxy.so
prophet/stan_model/cmdstan-2.26.1/stan/lib/stan_math/lib/tbb/tbbmalloc.def
prophet/stan_model/cmdstan-2.26.1/stan/lib/stan_math/lib/tbb/tbb_misc_ex.d
prophet/stan_model/cmdstan-2.26.1/stan/lib/stan_math/lib/tbb/concurrent_hash_map.d
prophet/stan_model/cmdstan-2.26.1/stan/lib/stan_math/lib/tbb/concurrent_queue.o
prophet/stan_model/cmdstan-2.26.1/stan/lib/stan_math/lib/tbb/tbb_statistics.d
prophet/stan_model/cmdstan-2.26.1/stan/lib/stan_math/lib/tbb/tbb_main.d
prophet/stan_model/cmdstan-2.26.1/stan/lib/stan_math/lib/tbb/concurrent_hash_map.o
prophet/stan_model/cmdstan-2.26.1/stan/lib/stan_math/lib/tbb/task.d
prophet/stan_model/cmdstan-2.26.1/stan/lib/stan_math/lib/tbb/task_group_context.o
prophet/stan_model/cmdstan-2.26.1/stan/lib/stan_math/lib/tbb/task_v2.o
prophet/stan_model/cmdstan-2.26.1/stan/lib/stan_math/lib/tbb/concurrent_queue_v2.o
prophet/stan_model/cmdstan-2.26.1/stan/lib/stan_math/lib/tbb/concurrent_vector.o
prophet_freddy-1.0.2.dist-info/LICENSE
prophet_freddy-1.0.2.dist-info/METADATA
prophet_freddy-1.0.2.dist-info/top_level.txt
prophet_freddy-1.0.2.dist-info/RECORD
prophet_freddy-1.0.2.dist-info/WHEEL
