Metadata-Version: 2.1
Name: prophet-freddy
Version: 1.0.2
Summary: Automatic Forecasting Procedure
Home-page: https://facebook.github.io/prophet/
Author: Sean J. Taylor <sjtz@pm.me>, Ben Letham <bletham@fb.com>
Author-email: sjtz@pm.me
License: MIT
Platform: UNKNOWN
Classifier: Programming Language :: Python
Classifier: Programming Language :: Python :: 3
Classifier: Programming Language :: Python :: 3.7
Classifier: Programming Language :: Python :: 3.8
Requires-Python: >=3
License-File: LICENSE
Requires-Dist: Cython (>=0.22)
Requires-Dist: cmdstanpy (==0.9.77)
Requires-Dist: numpy (>=1.15.4)
Requires-Dist: pandas (>=1.0.4)
Requires-Dist: matplotlib (>=2.0.0)
Requires-Dist: LunarCalendar (>=0.0.9)
Requires-Dist: convertdate (>=2.1.2)
Requires-Dist: holidays (>=0.11.3.1)
Requires-Dist: setuptools (>=42)
Requires-Dist: setuptools-git (>=1.2)
Requires-Dist: python-dateutil (>=2.8.0)
Requires-Dist: tqdm (>=4.36.1)
Requires-Dist: wheel (>=0.37.0)
